[
  {
    "Id": 1,
    "Prénom": "Tom",
    "Nom": "Boulay",
    "Tel": "0677351106",
    "Mail": "tomboulay1991@gmail.com",
    "Sexe": "M",
    "RFID": "FR1B75C01E",
    "Date RFID": "Thu Nov 30 2023 16:02:01 GMT+0100 (heure normale d’Europe centrale)",
    "Paiement": "74654732",
    "Club_Id": "1",
    "Club": "Roundnet Angers"
  },
  {
    "Id": 2,
    "Prénom": "Simon",
    "Nom": "Denieulle",
    "Tel": "0785310216",
    "Mail": "simondenieulle@gmail.com",
    "Sexe": "M",
    "RFID": "FRA4EF2205",
    "Date RFID": "Thu Nov 30 2023 16:02:01 GMT+0100 (heure normale d’Europe centrale)",
    "Paiement": "74654732",
    "Club_Id": "2",
    "Club": "Roundnet Angers"
  },
  {
    "Id": 3,
    "Prénom": "Marion",
    "Nom": "Deffrasnes",
    "Tel": "0634986409",
    "Mail": "marion.deffrasnes@gmail.com",
    "Sexe": "F",
    "RFID": "FRC2CA665F",
    "Date RFID": "Thu Nov 30 2023 16:02:01 GMT+0100 (heure normale d’Europe centrale)",
    "Paiement": "74654732",
    "Club_Id": "3",
    "Club": "Roundnet Angers"
  },
  {
    "Id": 4,
    "Prénom": "Alexandre",
    "Nom": "Savalle",
    "Tel": "06 59 30 53 96",
    "Mail": "alex.savalle@orange.fr",
    "Sexe": "Homme",
    "RFID": "FR16AB5DB3",
    "Date RFID": "Thu Nov 30 2023 16:11:38 GMT+0100 (heure normale d’Europe centrale)",
    "Paiement": "74938145",
    "Club_Id": "1",
    "Club": "Roundnet Clermont-Ferrand"
  },
  {
    "Id": 5,
    "Prénom": "Antoine",
    "Nom": "Grosse",
    "Tel": "06 49 95 22 89",
    "Mail": "antoine.grosse@gmail.com",
    "Sexe": "Homme",
    "RFID": "FR5D90F67D",
    "Date RFID": "Thu Nov 30 2023 16:11:38 GMT+0100 (heure normale d’Europe centrale)",
    "Paiement": "74938145",
    "Club_Id": "2",
    "Club": "Roundnet Clermont-Ferrand"
  },
  {
    "Id": 6,
    "Prénom": "Aurélia",
    "Nom": "Russinger",
    "Tel": "06 66 49 83 30",
    "Mail": "aurelia.russ@gmail.com",
    "Sexe": "Femme",
    "RFID": "FR2159BD38",
    "Date RFID": "Thu Nov 30 2023 16:11:38 GMT+0100 (heure normale d’Europe centrale)",
    "Paiement": "74938145",
    "Club_Id": "3",
    "Club": "Roundnet Clermont-Ferrand"
  },
  {
    "Id": 7,
    "Prénom": "Aurélien",
    "Nom": "Chaulet",
    "Tel": "06 38 80 44 71",
    "Mail": "aure.chaulet@gmail.com",
    "Sexe": "Homme",
    "RFID": "FR7DE142BC",
    "Date RFID": "Thu Nov 30 2023 16:11:38 GMT+0100 (heure normale d’Europe centrale)",
    "Paiement": "74938145",
    "Club_Id": "4",
    "Club": "Roundnet Clermont-Ferrand"
  },
  {
    "Id": 8,
    "Prénom": "Chloé",
    "Nom": "Legendre",
    "Tel": "0608982297",
    "Mail": "clengendr@gmail.com",
    "Sexe": "Femme",
    "RFID": "FR9CD016D1",
    "Date RFID": "Thu Nov 30 2023 16:11:38 GMT+0100 (heure normale d’Europe centrale)",
    "Paiement": "74938145",
    "Club_Id": "5",
    "Club": "Roundnet Clermont-Ferrand"
  },
  {
    "Id": 9,
    "Prénom": "Chloé",
    "Nom": "Trubert",
    "Tel": "06 58 92 79 12",
    "Mail": "chlo.trubert@gmail.com",
    "Sexe": "Femme",
    "RFID": "FR09212E74",
    "Date RFID": "Thu Nov 30 2023 16:11:38 GMT+0100 (heure normale d’Europe centrale)",
    "Paiement": "74938145",
    "Club_Id": "6",
    "Club": "Roundnet Clermont-Ferrand"
  },
  {
    "Id": 10,
    "Prénom": "Corentin",
    "Nom": "Chambost",
    "Tel": "06 89 38 43 65",
    "Mail": "chambost.corentin@gmail.com",
    "Sexe": "Homme",
    "RFID": "FR7C55810E",
    "Date RFID": "Thu Nov 30 2023 16:11:38 GMT+0100 (heure normale d’Europe centrale)",
    "Paiement": "74938145",
    "Club_Id": "7",
    "Club": "Roundnet Clermont-Ferrand"
  },
  {
    "Id": 11,
    "Prénom": "Cyril",
    "Nom": "Libert",
    "Tel": "06 03 17 64 72",
    "Mail": "w@cywil.org",
    "Sexe": "Homme",
    "RFID": "FR9CD016D1",
    "Date RFID": "Thu Nov 30 2023 16:11:38 GMT+0100 (heure normale d’Europe centrale)",
    "Paiement": "74938145",
    "Club_Id": "8",
    "Club": "Roundnet Clermont-Ferrand"
  },
  {
    "Id": 12,
    "Prénom": "Cédric",
    "Nom": "Trempont",
    "Tel": "06 41 50 31 31",
    "Mail": "cedric.trempont@gmail.com",
    "Sexe": "Homme",
    "RFID": "FR09212E74",
    "Date RFID": "Thu Nov 30 2023 16:11:38 GMT+0100 (heure normale d’Europe centrale)",
    "Paiement": "74938145",
    "Club_Id": "9",
    "Club": "Roundnet Clermont-Ferrand"
  },
  {
    "Id": 13,
    "Prénom": "Céline",
    "Nom": "Uch",
    "Tel": "07 68 02 37 03",
    "Mail": "uchceline@gmail.com",
    "Sexe": "Femme",
    "RFID": "FR48D32644",
    "Date RFID": "Thu Nov 30 2023 16:11:38 GMT+0100 (heure normale d’Europe centrale)",
    "Paiement": "74938145",
    "Club_Id": "10",
    "Club": "Roundnet Clermont-Ferrand"
  },
  {
    "Id": 14,
    "Prénom": "Elise",
    "Nom": "Martin",
    "Tel": "06 23 55 86 72",
    "Mail": "elise.martin444@gmail.com",
    "Sexe": "Femme",
    "RFID": "FR2DEB34BF",
    "Date RFID": "Thu Nov 30 2023 16:11:38 GMT+0100 (heure normale d’Europe centrale)",
    "Paiement": "74938145",
    "Club_Id": "11",
    "Club": "Roundnet Clermont-Ferrand"
  },
  {
    "Id": 15,
    "Prénom": "Enora",
    "Nom": "Le Cadre",
    "Tel": "06 32 03 20 32",
    "Mail": "enora.lecadre@orange.fr",
    "Sexe": "Femme",
    "RFID": "FR588A5104",
    "Date RFID": "Thu Nov 30 2023 16:11:38 GMT+0100 (heure normale d’Europe centrale)",
    "Paiement": "74938145",
    "Club_Id": "12",
    "Club": "Roundnet Clermont-Ferrand"
  },
  {
    "Id": 16,
    "Prénom": "Evans",
    "Nom": "Yeung",
    "Tel": "07 68 80 02 36",
    "Mail": "evans.yeung@gmail.com",
    "Sexe": "Homme",
    "RFID": "FR6FB66E75",
    "Date RFID": "Thu Nov 30 2023 16:11:38 GMT+0100 (heure normale d’Europe centrale)",
    "Paiement": "74938145",
    "Club_Id": "13",
    "Club": "Roundnet Clermont-Ferrand"
  },
  {
    "Id": 17,
    "Prénom": "Gilles",
    "Nom": "Bourdillon",
    "Tel": "06 70 76 50 20",
    "Mail": "Gilles.bourdillon@gmail.com",
    "Sexe": "Homme",
    "RFID": "FR612D611E",
    "Date RFID": "Thu Nov 30 2023 16:11:38 GMT+0100 (heure normale d’Europe centrale)",
    "Paiement": "74938145",
    "Club_Id": "14",
    "Club": "Roundnet Clermont-Ferrand"
  },
  {
    "Id": 18,
    "Prénom": "Guillaume",
    "Nom": "Sudre",
    "Tel": "0649885141",
    "Mail": "Guigui7896@gmail.com",
    "Sexe": "Homme",
    "RFID": "FR6414FC25",
    "Date RFID": "Thu Nov 30 2023 16:11:38 GMT+0100 (heure normale d’Europe centrale)",
    "Paiement": "74938145",
    "Club_Id": "15",
    "Club": "Roundnet Clermont-Ferrand"
  },
  {
    "Id": 19,
    "Prénom": "Jean",
    "Nom": "Kervella",
    "Tel": "06 68 05 78 11",
    "Mail": "jeankervella8@gmail.com",
    "Sexe": "Homme",
    "RFID": "FRCF006A02",
    "Date RFID": "Thu Nov 30 2023 16:11:38 GMT+0100 (heure normale d’Europe centrale)",
    "Paiement": "74938145",
    "Club_Id": "16",
    "Club": "Roundnet Clermont-Ferrand"
  },
  {
    "Id": 20,
    "Prénom": "Jeanne",
    "Nom": "Sylvestre",
    "Tel": "0637340324",
    "Mail": "jeannesilvestre@orange.fr",
    "Sexe": "Femme",
    "RFID": "FRF082F616",
    "Date RFID": "Thu Nov 30 2023 16:11:38 GMT+0100 (heure normale d’Europe centrale)",
    "Paiement": "74938145",
    "Club_Id": "17",
    "Club": "Roundnet Clermont-Ferrand"
  },
  {
    "Id": 21,
    "Prénom": "Kévin",
    "Nom": "Berger",
    "Tel": "06 31 69 86 24",
    "Mail": "bergerkevin63@gmail.com",
    "Sexe": "Homme",
    "RFID": "FRA3CF306F",
    "Date RFID": "Thu Nov 30 2023 16:11:38 GMT+0100 (heure normale d’Europe centrale)",
    "Paiement": "74938145",
    "Club_Id": "18",
    "Club": "Roundnet Clermont-Ferrand"
  },
  {
    "Id": 22,
    "Prénom": "Lou-Ann",
    "Nom": "Charvillat",
    "Tel": "06 10 40 36 86",
    "Mail": "lou-ann.charvillat@hotmail.fr",
    "Sexe": "Femme",
    "RFID": "FR19822525",
    "Date RFID": "Thu Nov 30 2023 16:11:38 GMT+0100 (heure normale d’Europe centrale)",
    "Paiement": "74938145",
    "Club_Id": "19",
    "Club": "Roundnet Clermont-Ferrand"
  },
  {
    "Id": 23,
    "Prénom": "Lucas",
    "Nom": "Rossignol",
    "Tel": "07 52 29 48 49",
    "Mail": "lucas.rossignol4@gmail.com",
    "Sexe": "Homme",
    "RFID": "FRA94E1C03",
    "Date RFID": "Thu Nov 30 2023 16:11:38 GMT+0100 (heure normale d’Europe centrale)",
    "Paiement": "74938145",
    "Club_Id": "20",
    "Club": "Roundnet Clermont-Ferrand"
  },
  {
    "Id": 24,
    "Prénom": "Lucas",
    "Nom": "Valente",
    "Tel": "06 46 59 80 06",
    "Mail": "lvalentes29@gmail.com",
    "Sexe": "Homme",
    "RFID": "FR19B3A72E",
    "Date RFID": "Thu Nov 30 2023 16:11:38 GMT+0100 (heure normale d’Europe centrale)",
    "Paiement": "74938145",
    "Club_Id": "21",
    "Club": "Roundnet Clermont-Ferrand"
  },
  {
    "Id": 25,
    "Prénom": "Lucile",
    "Nom": "Rouault",
    "Tel": "06 67 11 99 10",
    "Mail": "Lucilerouault19@gmail.com",
    "Sexe": "Femme",
    "RFID": "FRA94E1C03",
    "Date RFID": "Thu Nov 30 2023 16:11:38 GMT+0100 (heure normale d’Europe centrale)",
    "Paiement": "74938145",
    "Club_Id": "22",
    "Club": "Roundnet Clermont-Ferrand"
  },
  {
    "Id": 26,
    "Prénom": "Mahsa",
    "Nom": "Saber",
    "Tel": "07 73 82 09 28",
    "Mail": "misaghkeramati@gmail.com",
    "Sexe": "Femme",
    "RFID": "FR42333232",
    "Date RFID": "Thu Nov 30 2023 16:11:38 GMT+0100 (heure normale d’Europe centrale)",
    "Paiement": "74938145",
    "Club_Id": "23",
    "Club": "Roundnet Clermont-Ferrand"
  },
  {
    "Id": 27,
    "Prénom": "Margot",
    "Nom": "Paulin",
    "Tel": "06 85 97 74 40",
    "Mail": "margot.paulin@hotmail.fr",
    "Sexe": "Femme",
    "RFID": "FRC68D76AD",
    "Date RFID": "Thu Nov 30 2023 16:11:38 GMT+0100 (heure normale d’Europe centrale)",
    "Paiement": "74938145",
    "Club_Id": "24",
    "Club": "Roundnet Clermont-Ferrand"
  },
  {
    "Id": 28,
    "Prénom": "Marine",
    "Nom": "Hauchère",
    "Tel": "06 81 99 04 50",
    "Mail": "marine.hauchere@gmail.com",
    "Sexe": "Femme",
    "RFID": "FRDF218317",
    "Date RFID": "Thu Nov 30 2023 16:11:38 GMT+0100 (heure normale d’Europe centrale)",
    "Paiement": "74938145",
    "Club_Id": "25",
    "Club": "Roundnet Clermont-Ferrand"
  },
  {
    "Id": 29,
    "Prénom": "Mathis",
    "Nom": "Gigli",
    "Tel": "07 69 16 01 06",
    "Mail": "giglim29@gmail.com",
    "Sexe": "Homme",
    "RFID": "FR0780C2EE",
    "Date RFID": "Thu Nov 30 2023 16:11:38 GMT+0100 (heure normale d’Europe centrale)",
    "Paiement": "74938145",
    "Club_Id": "26",
    "Club": "Roundnet Clermont-Ferrand"
  },
  {
    "Id": 30,
    "Prénom": "Maxime",
    "Nom": "Giraud",
    "Tel": "06 47 02 83 23",
    "Mail": "giraud_maxime@orange.fr",
    "Sexe": "Homme",
    "RFID": "FR0780C2EE",
    "Date RFID": "Thu Nov 30 2023 16:11:38 GMT+0100 (heure normale d’Europe centrale)",
    "Paiement": "74938145",
    "Club_Id": "27",
    "Club": "Roundnet Clermont-Ferrand"
  },
  {
    "Id": 31,
    "Prénom": "Misagh",
    "Nom": "Keramati Sheyjani",
    "Tel": "07 48 62 56 01",
    "Mail": "misaghkeramati@gmail.com",
    "Sexe": "Homme",
    "RFID": "FRA56ECAA0",
    "Date RFID": "Thu Nov 30 2023 16:11:38 GMT+0100 (heure normale d’Europe centrale)",
    "Paiement": "74938145",
    "Club_Id": "28",
    "Club": "Roundnet Clermont-Ferrand"
  },
  {
    "Id": 32,
    "Prénom": "Mondane",
    "Nom": "Lejeune",
    "Tel": "06 73 36 97 90",
    "Mail": "mondane.lejeune@outlook.fr",
    "Sexe": "Femme",
    "RFID": "FR8A562FE0",
    "Date RFID": "Thu Nov 30 2023 16:11:38 GMT+0100 (heure normale d’Europe centrale)",
    "Paiement": "74938145",
    "Club_Id": "29",
    "Club": "Roundnet Clermont-Ferrand"
  },
  {
    "Id": 33,
    "Prénom": "Nicolas",
    "Nom": "Martin",
    "Tel": "06 61 05 83 96",
    "Mail": "nimartin.pro@gmail.com",
    "Sexe": "Homme",
    "RFID": "FREF135C21",
    "Date RFID": "Thu Nov 30 2023 16:11:38 GMT+0100 (heure normale d’Europe centrale)",
    "Paiement": "74938145",
    "Club_Id": "30",
    "Club": "Roundnet Clermont-Ferrand"
  },
  {
    "Id": 34,
    "Prénom": "Nicolas",
    "Nom": "Monnet",
    "Tel": "06 23 05 12 65",
    "Mail": "nicolasmonnet@outlook.fr",
    "Sexe": "Homme",
    "RFID": "FREF135C21",
    "Date RFID": "Thu Nov 30 2023 16:11:38 GMT+0100 (heure normale d’Europe centrale)",
    "Paiement": "74938145",
    "Club_Id": "31",
    "Club": "Roundnet Clermont-Ferrand"
  },
  {
    "Id": 35,
    "Prénom": "Olive",
    "Nom": "Makeu Sokamte",
    "Tel": "07 63 49 28 44",
    "Mail": "makeuolive1996@gmail.com",
    "Sexe": "Femme",
    "RFID": "FREA18257B",
    "Date RFID": "Thu Nov 30 2023 16:11:38 GMT+0100 (heure normale d’Europe centrale)",
    "Paiement": "74938145",
    "Club_Id": "32",
    "Club": "Roundnet Clermont-Ferrand"
  },
  {
    "Id": 36,
    "Prénom": "Pauline",
    "Nom": "Durin",
    "Tel": "07 86 28 37 30",
    "Mail": "pauline.durin@hotmail.fr",
    "Sexe": "Femme",
    "RFID": "FR8AAC9A75",
    "Date RFID": "Thu Nov 30 2023 16:11:38 GMT+0100 (heure normale d’Europe centrale)",
    "Paiement": "74938145",
    "Club_Id": "33",
    "Club": "Roundnet Clermont-Ferrand"
  },
  {
    "Id": 37,
    "Prénom": "Perrine",
    "Nom": "Lestrade",
    "Tel": "06 26 22 48 74",
    "Mail": "p25lestrade@gmail.com",
    "Sexe": "Femme",
    "RFID": "FR7D64B742",
    "Date RFID": "Thu Nov 30 2023 16:11:38 GMT+0100 (heure normale d’Europe centrale)",
    "Paiement": "74938145",
    "Club_Id": "34",
    "Club": "Roundnet Clermont-Ferrand"
  },
  {
    "Id": 38,
    "Prénom": "Quentin",
    "Nom": "Couyras",
    "Tel": "06 51 94 31 90",
    "Mail": "quentin.couyras09@gmail.com",
    "Sexe": "Homme",
    "RFID": "FRCC1953CF",
    "Date RFID": "Thu Nov 30 2023 16:11:38 GMT+0100 (heure normale d’Europe centrale)",
    "Paiement": "74938145",
    "Club_Id": "35",
    "Club": "Roundnet Clermont-Ferrand"
  },
  {
    "Id": 39,
    "Prénom": "Romain",
    "Nom": "Chaulet",
    "Tel": "06 65 35 77 59",
    "Mail": "romainchaulet@gmail.com",
    "Sexe": "Homme",
    "RFID": "FR29087299",
    "Date RFID": "Thu Nov 30 2023 16:11:38 GMT+0100 (heure normale d’Europe centrale)",
    "Paiement": "74938145",
    "Club_Id": "36",
    "Club": "Roundnet Clermont-Ferrand"
  },
  {
    "Id": 40,
    "Prénom": "Thomas",
    "Nom": "Grosse",
    "Tel": "07 81 97 42 77",
    "Mail": "th.grosse2002@gmail.com",
    "Sexe": "Homme",
    "RFID": "FR228437E5",
    "Date RFID": "Thu Nov 30 2023 16:11:38 GMT+0100 (heure normale d’Europe centrale)",
    "Paiement": "74938145",
    "Club_Id": "37",
    "Club": "Roundnet Clermont-Ferrand"
  },
  {
    "Id": 41,
    "Prénom": "Valentin",
    "Nom": "Bourrelier",
    "Tel": "06 29 57 04 33",
    "Mail": "valentin_oromis@yahoo.fr",
    "Sexe": "Homme",
    "RFID": "FRF48A796F",
    "Date RFID": "Thu Nov 30 2023 16:11:38 GMT+0100 (heure normale d’Europe centrale)",
    "Paiement": "74938145",
    "Club_Id": "38",
    "Club": "Roundnet Clermont-Ferrand"
  },
  {
    "Id": 42,
    "Prénom": "Zacharie",
    "Nom": "Seity",
    "Tel": "06 73 70 94 98",
    "Mail": "zacharie.seity@gmail.com",
    "Sexe": "Homme",
    "RFID": "FRF3BA01A6",
    "Date RFID": "Thu Nov 30 2023 16:11:38 GMT+0100 (heure normale d’Europe centrale)",
    "Paiement": "74938145",
    "Club_Id": "39",
    "Club": "Roundnet Clermont-Ferrand"
  }
]